psi_eligibility/__init__.py
psi_eligibility/api_client.py
psi_eligibility/configuration.py
psi_eligibility/rest.py
psi_eligibility/api/__init__.py
psi_eligibility/api/default_api.py
psi_eligibility/models/__init__.py
psi_eligibility/models/additional_attribute_model.py
psi_eligibility/models/candidate_model.py
psi_eligibility/models/eligibility_model.py
psi_eligibility/models/eligibility_response_model.py
psi_eligibility/models/error_model.py
psi_eligibility/models/existing_eligibility_model.py
psi_eligibility/models/test_launch_info_model.py
test/__init__.py
test/test_additional_attribute_model.py
test/test_candidate_model.py
test/test_default_api.py
test/test_eligibility_model.py
test/test_eligibility_response_model.py
test/test_error_model.py
test/test_existing_eligibility_model.py
test/test_test_launch_info_model.py
psi_eligibility-1.0.0.dist-info/METADATA
psi_eligibility-1.0.0.dist-info/WHEEL
psi_eligibility-1.0.0.dist-info/top_level.txt
psi_eligibility-1.0.0.dist-info/RECORD
