Metadata-Version: 2.1
Name: psi-eligibility
Version: 1.0.0
Summary: PSI Candidate Rest Eligibility Service
Home-page: UNKNOWN
Author: UNKNOWN
Author-email: morahood@gmail.com
License: UNKNOWN
Keywords: Swagger,PSI Candidate Rest Eligibility Service
Platform: UNKNOWN
Requires-Dist: certifi (>=2017.4.17)
Requires-Dist: python-dateutil (>=2.1)
Requires-Dist: six (>=1.10)
Requires-Dist: urllib3 (>=1.23)
